crispy_models/__init__.py
crispy_models/models.py
crispy_models/py.typed
crispy_models/version.py
crispy_models-0.1.14.dist-info/LICENSE.txt
crispy_models-0.1.14.dist-info/METADATA
crispy_models-0.1.14.dist-info/WHEEL
crispy_models-0.1.14.dist-info/top_level.txt
crispy_models-0.1.14.dist-info/RECORD
