Metadata-Version: 2.1
Name: crispy-models
Version: 0.1.14
Summary: Shared code for CRISPy web service
Home-page: https://github.com/secondarymetabolites/crispy-models/
Author: Kai Blin
Author-email: kblin@biosustain.dtu.dk
License: GNU Affero General Public License
Classifier: Programming Language :: Python
Classifier: Programming Language :: Python :: 3
Classifier: Development Status :: 4 - Beta
Classifier: Intended Audience :: Science/Research
Classifier: Topic :: Scientific/Engineering :: Bio-Informatics
Classifier: License :: OSI Approved :: GNU Affero General Public License v3 or later (AGPLv3+)
Classifier: Operating System :: OS Independent
License-File: LICENSE.txt
Provides-Extra: packaging
Requires-Dist: twine ; extra == 'packaging'
Provides-Extra: testing
Requires-Dist: fakeredis ; extra == 'testing'
Requires-Dist: flake8 ; extra == 'testing'
Requires-Dist: mypy ; extra == 'testing'
Requires-Dist: pytest ; extra == 'testing'
Requires-Dist: pytest-cov ; extra == 'testing'
